nonebot_plugin_SimpleToWrite/__init__.py
nonebot_plugin_SimpleToWrite/help/HYWH-65W.ttf
nonebot_plugin_SimpleToWrite/help/help.py
nonebot_plugin_SimpleToWrite/teach/HYWH-65W.ttf
nonebot_plugin_SimpleToWrite/teach/teach.py
nonebot_plugin_SimpleToWrite/teach/教学文件/变量大全-[戳一戳]/文字.txt
nonebot_plugin_SimpleToWrite/teach/教学文件/变量大全-asif 比较式/文字.txt
nonebot_plugin_SimpleToWrite/teach/教学文件/变量大全-geturl/文字.txt
nonebot_plugin_SimpleToWrite/teach/教学文件/变量大全-sendtext  发送文本/文字.txt
nonebot_plugin_SimpleToWrite/teach/教学文件/变量大全/文字.txt
nonebot_plugin_simpletowrite-0.2.1.dist-info/METADATA
nonebot_plugin_simpletowrite-0.2.1.dist-info/WHEEL
nonebot_plugin_simpletowrite-0.2.1.dist-info/entry_points.txt
nonebot_plugin_simpletowrite-0.2.1.dist-info/licenses/LICENSE
nonebot_plugin_simpletowrite-0.2.1.dist-info/RECORD
